LICENSE.md
README.md
pyproject.toml
setup.cfg
setup.py
dsutils_ms/__init__.py
dsutils_ms.egg-info/PKG-INFO
dsutils_ms.egg-info/SOURCES.txt
dsutils_ms.egg-info/dependency_links.txt
dsutils_ms.egg-info/requires.txt
dsutils_ms.egg-info/top_level.txt
dsutils_ms.egg-info/zip-safe
dsutils_ms/adapters/__init__.py
dsutils_ms/adapters/dynamo.py
dsutils_ms/adapters/google_sheets.py
dsutils_ms/adapters/interface.py
dsutils_ms/adapters/mysql.py
dsutils_ms/adapters/s3.py
dsutils_ms/helpers/__init__.py
dsutils_ms/helpers/cleaning.py
dsutils_ms/helpers/dataframe.py
dsutils_ms/helpers/datetime.py
dsutils_ms/helpers/dict.py
dsutils_ms/helpers/env.py
dsutils_ms/helpers/google_chat.py
dsutils_ms/helpers/log.py
tests/test_cleaning.py
tests/test_datetime.py
tests/test_dict.py
tests/test_dynamo.py
tests/test_env.py
tests/test_google_chat.py
tests/test_google_sheets.py
tests/test_mysql.py
tests/test_s3.py