Metadata-Version: 2.1
Name: dsutils-ms
Version: 1.10
Summary: My Data Science Utils
Home-page: https://www.linkedin.com/in/matheusserpa/
Author: Matheus Serpa
Author-email: matheusserpa@gmail.com
License: GNU General Public License v3.0
Keywords: data science,data engineering,machine learning,data analysis,data visualization
Classifier: License :: OSI Approved :: GNU General Public License v3 (GPLv3)
Classifier: Programming Language :: Python :: 3
Classifier: Operating System :: OS Independent
License-File: LICENSE.md
